crypto_utils/__init__.py
crypto_utils/crypto_utils.py
aes_crypto_utils-0.1.0.dist-info/LICENSE
aes_crypto_utils-0.1.0.dist-info/METADATA
aes_crypto_utils-0.1.0.dist-info/WHEEL
aes_crypto_utils-0.1.0.dist-info/top_level.txt
aes_crypto_utils-0.1.0.dist-info/RECORD
