Metadata-Version: 2.1
Name: aes_crypto_utils
Version: 0.1.0
Summary: A simple encryption and decryption utility library.
Home-page: 
Author: Pradeep Pujari
Author-email: pradeep.m.pujari@gmail.com
Classifier: Programming Language :: Python :: 3
Classifier: License :: OSI Approved :: MIT License
Classifier: Operating System :: OS Independent
Requires-Python: >=3.6
License-File: LICENSE
Requires-Dist: cryptography >=3.0
